Metadata-Version: 2.1
Name: EthAlexandria
Version: 0.0.5
Summary: A project to decentralize and distribute literary infrastructure powered by EVM and IPFS.
Home-page: https://github.com/ObiajuluM/Alexandria
Author: Obiajulu_M
Author-email: oambanefo@outlook.com
License: MIT
Platform: UNKNOWN
Classifier: Programming Language :: Python :: 3
Classifier: License :: OSI Approved :: MIT License
Classifier: Operating System :: OS Independent
Requires-Python: >=3.8
License-File: LICENSE
